django_giji_auth
